Workbook

Sheet Premissas
A1: Premissa | B1: Valor | C1: Unidade | D1: Observação
A2: Câmbio efetivo | B2: 5.5 | C2: BRL/USD | D2: Inclui spread/impostos; substituir pela taxa contratada
A3: CAPEX local | B3: 20000 | C3: BRL | D3: Hardware, montagem e periféricos
A4: Vida útil | B4: 36 | C4: meses | D4: Use 24/36/48 para sensibilidade
A5: Valor residual | B5: 0 | C5: BRL | D5: Estimativa ao final da vida útil
A6: Potência média | B6: 0.65 | C6: kW | D6: Medida na tomada, não TDP
A7: Horas/dia | B7: 12 | C7: h | D7: Carga média
A8: Dias/mês | B8: 26 | C8: dias | D8: Dias efetivos
A9: Tarifa efetiva | B9: 1.05 | C9: BRL/kWh | D9: Energia + impostos + bandeira
A10: Refrigeração mensal | B10: 150 | C10: BRL | D10: Parcela atribuída à IA
A11: Manutenção/garantia mensal | B11: 250 | C11: BRL | D11: Reserva média
A12: Operação/espaço mensal | B12: 600 | C12: BRL | D12: Equipe, rack, internet, backup
A13: Fator utilização | B13: 0.5 | C13: % | D13: Tokens efetivos/capacidade teórica
... A17: Velocidade decode | B17: 35 | C17: tokens/s | D17: Medida no modelo e quantização alvo
A19: Data de consulta | B19: 2026-09-01 | C19: AAAA-MM-DD | D19: Preço oficial consultado em openai.com/api/pricing
A20: Batch API | B20: 0.5 | C20: fator | D20: 50% do standard para workloads assíncronos, sujeito às condições oficiais
A21: Sobretaxa contexto longo — entrada | B21: 1 | C21: fator | D21: Fator sobre o preço de input acima do limite de preço-base (1 = sem sobretaxa)
A22: Cache writes | B22: 0 | C22: US$/M | D22: Preencher quando aplicável; não presumir custo zero sem confirmação
A23: Sobretaxa contexto longo — cached | B23: 1 | C23: fator | D23: Fator sobre o preço de cached input (1 = sem sobretaxa)
A24: Sobretaxa contexto longo — saída | B24: 1 | C24: fator | D24: Fator sobre o preço de output (1 = sem sobretaxa)

Sheet API_OpenAI
A1: Modelo | B1: Input US$/M | C1: Cached US$/M | D1: Output US$/M | E1: Custo mensal USD | F1: Custo mensal BRL | G1: Custo mensal BRL (Batch)
A2: GPT-5.6 Sol | B2: 4 | C2: 0.4 | D2: 20 | E2: =(Premissas!$B$14*B2*Premissas!$B$21)+(Premissas!$B$15*(C2+Premissas!$B$22)*Premissas!$B$23)+(Premissas!$B$16*D2*Premissas!$B$24) | F2: =E2*Premissas!$B$2 | G2: =F2*Premissas!$B$20
A3: GPT-5.6 Terra | B3: 2 | C3: 0.2 | D3: 12 | E3: =(Premissas!$B$14*B3*Premissas!$B$21)+(Premissas!$B$15*(C3+Premissas!$B$22)*Premissas!$B$23)+(Premissas!$B$16*D3*Premissas!$B$24) | F3: =E3*Premissas!$B$2 | G3: =F3*Premissas!$B$20
A4: GPT-5.6 Luna | B4: 0.2 | C4: 0.02 | D4: 1.2 | E4: =(Premissas!$B$14*B4*Premissas!$B$21)+(Premissas!$B$15*(C4+Premissas!$B$22)*Premissas!$B$23)+(Premissas!$B$16*D4*Premissas!$B$24) | F4: =E4*Premissas!$B$2 | G4: =F4*Premissas!$B$20

Sheet Local
A1: Item | B1: Fórmula | C1: Custo mensal BRL
A2: CAPEX amortizado | B2: (CAPEX − valor residual) / vida útil | C2: =(Premissas!B3-Premissas!B5)/Premissas!B4
A3: Energia | B3: kW × h/dia × dias × tarifa | C3: =Premissas!B6*Premissas!B7*Premissas!B8*Premissas!B9
A4: Refrigeração | C4: =Premissas!B10
A5: Manutenção/garantia | C5: =Premissas!B11
A6: Operação/espaço | C6: =Premissas!B12
A7: TCO local | C7: =SUM(C2:C6)
A8: Capacidade mensal | B8: tokens/s × 3600 × h/dia × dias × utilização | C8: =Premissas!B17*3600*Premissas!B7*Premissas!B8*Premissas!B13
A9: Custo local por M tokens | B9: TCO / (capacidade/1M) | C9: =C7/(C8/1000000)

Sheet Break_even
A1: Modelo | B1: Custo API BRL/mês | C1: TCO local BRL/mês | D1: Economia API-local | E1: Break-even tokens M/mês (mix atual) | F1: Status | G1: Break-even tokens M/mês (Batch) | H1: Custo API blended BRL/M (mix atual)
A2: =API_OpenAI!A2 | B2: =API_OpenAI!F2 | C2: =Local!C7 | D2: =B2-C2 | E2: =C2/H2 | F2: =IF(D2>0,"Local tende a vencer no custo direto","API tende a vencer no custo direto") | G2: =E2/Premissas!$B$20 | H2: =API_OpenAI!F2/(Premissas!$B$14+Premissas!$B$15+Premissas!$B$16)
A3: =API_OpenAI!A3 | B3: =API_OpenAI!F3 | C3: =Local!C7 | D3: =B3-C3 | E3: =C3/H3 | F3: =IF(D3>0,"Local tende a vencer no custo direto","API tende a vencer no custo direto") | G3: =E3/Premissas!$B$20 | H3: =API_OpenAI!F3/(Premissas!$B$14+Premissas!$B$15+Premissas!$B$16)
A4: =API_OpenAI!A4 | B4: =API_OpenAI!F4 | C4: =Local!C7 | D4: =B4-C4 | E4: =C4/H4 | F4: =IF(D4>0,"Local tende a vencer no custo direto","API tende a vencer no custo direto") | G4: =E4/Premissas!$B$20 | H4: =API_OpenAI!F4/(Premissas!$B$14+Premissas!$B$15+Premissas!$B$16)

Sheet Sensibilidade
A1: Câmbio BRL/USD | B1: Luna BRL/mês | C1: Terra BRL/mês | D1: Sol BRL/mês | E1: TCO local BRL/mês | F1: Break-even Sol M/mês | G1: Break-even Terra M/mês | H1: Break-even Luna M/mês
A2: 4.4 | B2: =API_OpenAI!$E$4*$A2 | C2: =API_OpenAI!$E$3*$A2 | D2: =API_OpenAI!$E$2*$A2 | E2: =Local!$C$7 | F2: =E2/(D2/(Premissas!$B$14+Premissas!$B$15+Premissas!$B$16)) | G2: =E2/(C2/(Premissas!$B$14+Premissas!$B$15+Premissas!$B$16)) | H2: =E2/(B2/(Premissas!$B$14+Premissas!$B$15+Premissas!$B$16))
A3: 4.95 | B3: =API_OpenAI!$E$4*$A3 | C3: =API_OpenAI!$E$3*$A3 | D3: =API_OpenAI!$E$2*$A3 | E3: =Local!$C$7 | F3: =E3/(D3/(Premissas!$B$14+Premissas!$B$15+Premissas!$B$16)) | G3: =E3/(C3/(Premissas!$B$14+Premissas!$B$15+Premissas!$B$16)) | H3: =E3/(B3/(Premissas!$B$14+Premissas!$B$15+Premissas!$B$16))
A4: 5.5 | B4: =API_OpenAI!$E$4*$A4 | C4: =API_OpenAI!$E$3*$A4 | D4: =API_OpenAI!$E$2*$A4 | E4: =Local!$C$7 | F4: =E4/(D4/(Premissas!$B$14+Premissas!$B$15+Premissas!$B$16)) | G4: =E4/(C4/(Premissas!$B$14+Premissas!$B$15+Premissas!$B$16)) | H4: =E4/(B4/(Premissas!$B$14+Premissas!$B$15+Premissas!$B$16))
A5: 6.05 | B5: =API_OpenAI!$E$4*$A5 | C5: =API_OpenAI!$E$3*$A5 | D5: =API_OpenAI!$E$2*$A5 | E5: =Local!$C$7 | F5: =E5/(D5/(Premissas!$B$14+Premissas!$B$15+Premissas!$B$16)) | G5: =E5/(C5/(Premissas!$B$14+Premissas!$B$15+Premissas!$B$16)) | H5: =E5/(B5/(Premissas!$B$14+Premissas!$B$15+Premissas!$B$16))
A6: 6.6 | B6: =API_OpenAI!$E$4*$A6 | C6: =API_OpenAI!$E$3*$A6 | D6: =API_OpenAI!$E$2*$A6 | E6: =Local!$C$7 | F6: =E6/(D6/(Premissas!$B$14+Premissas!$B$15+Premissas!$B$16)) | G6: =E6/(C6/(Premissas!$B$14+Premissas!$B$15+Premissas!$B$16)) | H6: =E6/(B6/(Premissas!$B$14+Premissas!$B$15+Premissas!$B$16))
A8: Vida útil (meses) | B8: CAPEX amortizado BRL/mês | C8: TCO local BRL/mês | D8: Break-even Sol M/mês | E8: Break-even Terra M/mês | F8: Break-even Luna M/mês
A9: 24 | B9: =(Premissas!$B$3-Premissas!$B$5)/A9 | C9: =Local!$C$7-Local!$C$2+B9 | D9: =C9/Break_even!$H$2 | E9: =C9/Break_even!$H$3 | F9: =C9/Break_even!$H$4
A10: 36 | B10: =(Premissas!$B$3-Premissas!$B$5)/A10 | C10: =Local!$C$7-Local!$C$2+B10 | D10: =C10/Break_even!$H$2 | E10: =C10/Break_even!$H$3 | F10: =C10/Break_even!$H$4
A11: 48 | B11: =(Premissas!$B$3-Premissas!$B$5)/A11 | C11: =Local!$C$7-Local!$C$2+B11 | D11: =C11/Break_even!$H$2 | E11: =C11/Break_even!$H$3 | F11: =C11/Break_even!$H$4
A13: Fator utilização | B13: Capacidade M tokens/mês | C13: Custo local BRL/M tokens | D13: API Sol blended BRL/M | E13: API Terra blended BRL/M | F13: API Luna blended BRL/M
A14: 0.1 | B14: =Premissas!$B$17*3600*Premissas!$B$7*Premissas!$B$8*A14/1000000 | C14: =Local!$C$7/B14 | D14: =Break_even!$H$2 | E14: =Break_even!$H$3 | F14: =Break_even!$H$4
A15: 0.25 | B15: =Premissas!$B$17*3600*Premissas!$B$7*Premissas!$B$8*A15/1000000 | C15: =Local!$C$7/B15 | D15: =Break_even!$H$2 | E15: =Break_even!$H$3 | F15: =Break_even!$H$4
A16: 0.5 | B16: =Premissas!$B$17*3600*Premissas!$B$7*Premissas!$B$8*A16/1000000 | C16: =Local!$C$7/B16 | D16: =Break_even!$H$2 | E16: =Break_even!$H$3 | F16: =Break_even!$H$4
A17: 0.8 | B17: =Premissas!$B$17*3600*Premissas!$B$7*Premissas!$B$8*A17/1000000 | C17: =Local!$C$7/B17 | D17: =Break_even!$H$2 | E17: =Break_even!$H$3 | F17: =Break_even!$H$4
A19: Tarifa BRL/kWh | B19: Energia BRL/mês | C19: TCO local BRL/mês | D19: Break-even Sol M/mês | E19: Break-even Terra M/mês | F19: Break-even Luna M/mês
A20: =Premissas!$B$9*0.7 | B20: =Premissas!$B$6*Premissas!$B$7*Premissas!$B$8*A20 | C20: =Local!$C$7-Local!$C$3+B20 | D20: =C20/Break_even!$H$2 | E20: =C20/Break_even!$H$3 | F20: =C20/Break_even!$H$4
A21: =Premissas!$B$9*0.85 | B21: =Premissas!$B$6*Premissas!$B$7*Premissas!$B$8*A21 | C21: =Local!$C$7-Local!$C$3+B21 | D21: =C21/Break_even!$H$2 | E21: =C21/Break_even!$H$3 | F21: =C21/Break_even!$H$4
A22: =Premissas!$B$9*1 | B22: =Premissas!$B$6*Premissas!$B$7*Premissas!$B$8*A22 | C22: =Local!$C$7-Local!$C$3+B22 | D22: =C22/Break_even!$H$2 | E22: =C22/Break_even!$H$3 | F22: =C22/Break_even!$H$4
A23: =Premissas!$B$9*1.15 | B23: =Premissas!$B$6*Premissas!$B$7*Premissas!$B$8*A23 | C23: =Local!$C$7-Local!$C$3+B23 | D23: =C23/Break_even!$H$2 | E23: =C23/Break_even!$H$3 | F23: =C23/Break_even!$H$4
A24: =Premissas!$B$9*1.3 | B24: =Premissas!$B$6*Premissas!$B$7*Premissas!$B$8*A24 | C24: =Local!$C$7-Local!$C$3+B24 | D24: =C24/Break_even!$H$2 | E24: =C24/Break_even!$H$3 | F24: =C24/Break_even!$H$4

Sheet README
A1: Calculadora TCO local versus API OpenAI
A2: Data da versão | B2: 2026-09-01
A3: Unidades | B3: Tokens em milhões; moeda em BRL salvo onde indicado.
A4: Nota | B4: Recalcular no Excel/LibreOffice; preços são mutáveis e devem ser revalidados.
A5: Revisão | B5: 2026-09-01 (rev. 2): câmbio aplicado ao break-even; valor residual no CAPEX; coluna Batch; fatores de contexto longo por categoria; sensibilidade por câmbio, vida útil, utilização e tarifa.
A6: Recalcular | B6: Arquivo salvo sem valores em cache; abra no Excel/LibreOffice e force o recálculo antes de ler resultados.
